githubapps/__init__.py
githubapps/adapter.py
githubapps/errors.py
githubapps.py-1.1.0.dist-info/LICENSE
githubapps.py-1.1.0.dist-info/METADATA
githubapps.py-1.1.0.dist-info/WHEEL
githubapps.py-1.1.0.dist-info/top_level.txt
githubapps.py-1.1.0.dist-info/RECORD
