Metadata-Version: 2.1
Name: githubapps.py
Version: 1.1.0
Summary: This is a wrapper for the Github Apps API.
Home-page: https://github.com/RTa-technology/githubapps.py
Author: RTa-technology
License: MIT
Platform: UNKNOWN
Classifier: Programming Language :: Python :: 3.8
Classifier: Programming Language :: Python :: 3.9
Classifier: License :: OSI Approved :: MIT License
Classifier: Operating System :: OS Independent
License-File: LICENSE
Requires-Dist: PyJWT
Requires-Dist: aiohttp
Requires-Dist: requests
Requires-Dist: cryptography
Requires-Dist: httpx
